README.md
setup.py
enos_poseidon.egg-info/PKG-INFO
enos_poseidon.egg-info/SOURCES.txt
enos_poseidon.egg-info/dependency_links.txt
enos_poseidon.egg-info/not-zip-safe
enos_poseidon.egg-info/requires.txt
enos_poseidon.egg-info/top_level.txt
poseidon/__init__.py
poseidon/poseidon.py